hitboxy/ChatClient.py
hitboxy/MultiChannelChatClient.py
hitboxy/__init__.py
hitboxy-0.1.20.dist-info/DESCRIPTION.rst
hitboxy-0.1.20.dist-info/METADATA
hitboxy-0.1.20.dist-info/RECORD
hitboxy-0.1.20.dist-info/WHEEL
hitboxy-0.1.20.dist-info/dependency_links.txt
hitboxy-0.1.20.dist-info/metadata.json
hitboxy-0.1.20.dist-info/top_level.txt
