Metadata-Version: 2.0
Name: hitboxy
Version: 0.1.20
Summary: Wrapper around the Hitbox API
Home-page: https://bitbucket.org/Uranoxyd/hitboxy
Author: David Ewelt
Author-email: uranoxyd@gmail.com
License: BSD
Keywords: hitbox hitbox.tv api
Platform: UNKNOWN
Classifier: Development Status :: 3 - Alpha
Classifier: Intended Audience :: Developers
Classifier: Topic :: Software Development :: Libraries :: Python Modules
Classifier: Programming Language :: Python :: 2
Classifier: Programming Language :: Python :: 2.6
Classifier: Programming Language :: Python :: 2.7
Classifier: Programming Language :: Python :: 3
Provides-Extra: chatclient
Requires-Dist: websocket-client (>=0.35.0); extra == 'chatclient'
